AUTHORS
COPYING
ChangeLog.in
MANIFEST.in
NEWS
README
TODO
kaa-imlib2.spec
setup.cfg
setup.py
doc/Makefile
doc/conf.py
doc/font.rst
doc/image.rst
doc/index.rst
doc/_templates/layout.html
kaa_imlib2.egg-info/PKG-INFO
kaa_imlib2.egg-info/SOURCES.txt
kaa_imlib2.egg-info/dependency_links.txt
kaa_imlib2.egg-info/namespace_packages.txt
kaa_imlib2.egg-info/not-zip-safe
kaa_imlib2.egg-info/top_level.txt
src/__init__.py
src/config.h
src/font.c
src/font.h
src/font.py
src/image.c
src/image.h
src/image.py
src/imlib2.c
src/imlib2.h
src/rawformats.c
src/rawformats.h
src/svg.c
src/version.py
test/test.py