Metadata-Version: 1.0
Name: kaa-imlib2
Version: 0.3.0dev-r4385-20100905
Summary: Python bindings for Imlib2, a powerful and efficient image processing library.
Home-page: http://doc.freevo.org/api/kaa/imlib2/
Author: Freevo Development Team
Author-email: freevo-devel@lists.sourceforge.net
License: LGPL
Platform: UNKNOWN
